dfpyre/__init__.py
dfpyre/core/actiondump.py
dfpyre/core/codeblock.py
dfpyre/core/items.py
dfpyre/core/template.py
dfpyre/data/actiondump_min.json
dfpyre/data/deprecated_actions.json
dfpyre/data/method_templates/action.txt
dfpyre/data/method_templates/conditional.txt
dfpyre/data/method_templates/event.txt
dfpyre/data/method_templates/notarget_action.txt
dfpyre/data/method_templates/notarget_conditional.txt
dfpyre/data/method_templates/repeat.txt
dfpyre/data/method_templates/repeat_while.txt
dfpyre/data/method_templates/select_obj_subaction.txt
dfpyre/data/particle_class/particle_class_template.py
dfpyre/data/particle_class/particle_method.txt
dfpyre/export/action_classes.py
dfpyre/export/block_functions.py
dfpyre/export/particle_item.py
dfpyre/gen/action_gen_data.py
dfpyre/gen/action_literals.py
dfpyre/gen/gen_data.py
dfpyre/gen/particle_gen_data.py
dfpyre/scripts/action_gen.py
dfpyre/scripts/action_literal_gen.py
dfpyre/scripts/particle_gen.py
dfpyre/tool/scriptgen.py
dfpyre/tool/slice.py
dfpyre/util/codeitem.py
dfpyre/util/style.py
dfpyre/util/util.py
dfpyre-0.11.0.dist-info/METADATA
dfpyre-0.11.0.dist-info/WHEEL
dfpyre-0.11.0.dist-info/licenses/LICENSE
dfpyre-0.11.0.dist-info/RECORD
