Metadata-Version: 2.4
Name: dfpyre
Version: 0.11.0
Summary: A package for creating and modifying code templates for the DiamondFire Minecraft server.
License-Expression: MIT
License-File: LICENSE
Keywords: diamondfire,minecraft,template,item
Author: Amp
Requires-Python: >=3.10
Classifier: Programming Language :: Python :: 3
Classifier: Programming Language :: Python :: 3.10
Classifier: Programming Language :: Python :: 3.11
Classifier: Programming Language :: Python :: 3.12
Classifier: Programming Language :: Python :: 3.13
Classifier: Programming Language :: Python :: 3.14
Provides-Extra: dev
Requires-Dist: mcitemlib (>=0.5.2)
Requires-Dist: pytest (>=9.0.2) ; extra == "dev"
Requires-Dist: rapidnbt (>=1.3.5)
Requires-Dist: twine (>=6.2.0) ; extra == "dev"
Requires-Dist: websocket-client (>=1.9.0)
Project-URL: Repository, https://github.com/Amp63/pyre
